dash_text_to_speech/DashTextToSpeech.py
dash_text_to_speech/__init__.py
dash_text_to_speech/_imports_.py
dash_text_to_speech/async-DashTextToSpeech.js
dash_text_to_speech/async-DashTextToSpeech.js.map
dash_text_to_speech/dash_text_to_speech.min.js
dash_text_to_speech/dash_text_to_speech.min.js.map
dash_text_to_speech/metadata.json
dash_text_to_speech/package-info.json
dash_text_to_speech-0.0.1.dist-info/LICENSE
dash_text_to_speech-0.0.1.dist-info/METADATA
dash_text_to_speech-0.0.1.dist-info/WHEEL
dash_text_to_speech-0.0.1.dist-info/top_level.txt
dash_text_to_speech-0.0.1.dist-info/RECORD
