Metadata-Version: 2.1
Name: dash-text-to-speech
Version: 0.0.1
Summary: my dash mic recorder
Author: me <me@gmail.com>
License: MIT
Classifier: Framework :: Dash
License-File: LICENSE
